w3ezpz/__init__.py
w3ezpz-0.0.1a0.dist-info/WHEEL
w3ezpz-0.0.1a0.dist-info/METADATA
w3ezpz-0.0.1a0.dist-info/RECORD
