Metadata-Version: 2.1
Name: w3ezpz
Version: 0.0.1a0
Summary: web 3 ezpz
Author: killingtime
Author-email: killingtime-sc@pm.me
Requires-Python: >=3.10,<3.11
Classifier: Programming Language :: Python :: 3
Classifier: Programming Language :: Python :: 3.10
Requires-Dist: web3 (>=5.27.0,<6.0.0)
